hra_api_client/__init__.py
hra_api_client/api_client.py
hra_api_client/api_response.py
hra_api_client/configuration.py
hra_api_client/exceptions.py
hra_api_client/py.typed
hra_api_client/rest.py
hra_api_client/api/__init__.py
hra_api_client/api/ds_graph_api.py
hra_api_client/api/hra_kg_api.py
hra_api_client/api/hra_pop_api.py
hra_api_client/api/v1_api.py
hra_api_client/models/__init__.py
hra_api_client/models/aggregate_count.py
hra_api_client/models/cell_summary_report.py
hra_api_client/models/cell_summary_report_request.py
hra_api_client/models/cell_summary_row.py
hra_api_client/models/database_status.py
hra_api_client/models/digital_object_info.py
hra_api_client/models/digital_objects_json_ld.py
hra_api_client/models/error_message.py
hra_api_client/models/filter.py
hra_api_client/models/flat_spatial_placement.py
hra_api_client/models/get_spatial_placement_request.py
hra_api_client/models/id_label_pair.py
hra_api_client/models/mesh3d_cell_population_request.py
hra_api_client/models/min_max.py
hra_api_client/models/ontology_tree.py
hra_api_client/models/ontology_tree_node.py
hra_api_client/models/session_token.py
hra_api_client/models/session_token_request.py
hra_api_client/models/source_similarity_row.py
hra_api_client/models/sparql_query_request.py
hra_api_client/models/spatial_entity.py
hra_api_client/models/spatial_entity_common.py
hra_api_client/models/spatial_entity_creator.py
hra_api_client/models/spatial_entity_dimensions.py
hra_api_client/models/spatial_object_reference.py
hra_api_client/models/spatial_placement.py
hra_api_client/models/spatial_placement_common.py
hra_api_client/models/spatial_placement_rotation.py
hra_api_client/models/spatial_placement_scaling.py
hra_api_client/models/spatial_placement_translation.py
hra_api_client/models/spatial_scene_node.py
hra_api_client/models/spatial_search.py
hra_api_client/models/tissue_block.py
hra_api_client/models/tissue_common.py
hra_api_client/models/tissue_dataset.py
hra_api_client/models/tissue_donor.py
hra_api_client-0.16.1.dist-info/METADATA
hra_api_client-0.16.1.dist-info/WHEEL
hra_api_client-0.16.1.dist-info/top_level.txt
hra_api_client-0.16.1.dist-info/RECORD
