Metadata-Version: 2.1
Name: hra-api-client
Version: 0.16.1
Summary: HRA-API
Home-page: https://pypi.org/project/hra-api-client/
Author: HuBMAP Help Desk
Author-email: help@hubmapconsortium.org
License: MIT License
Keywords: OpenAPI,OpenAPI-Generator,HRA-API
Platform: UNKNOWN
Requires-Dist: lazy-imports (<2,>=1)
Requires-Dist: pydantic (>=2)
Requires-Dist: python-dateutil (>=2.8.2)
Requires-Dist: typing-extensions (>=4.7.1)
Requires-Dist: urllib3 (<3.0.0,>=2.1.0)
